[
  {
    "line": 2,
    "elements": [
      {
        "line": 4,
        "name": "",
        "description": "",
        "type": "background",
        "keyword": "Background",
        "steps": [
          {
            "result": {
              "duration": 283187000,
              "status": "passed"
            },
            "line": 5,
            "name": "User is on Retail website",
            "match": {
              "location": "step.definition.DesktopStepDef.user_is_on_retail_website()"
            },
            "keyword": "Given "
          },
          {
            "result": {
              "duration": 607003000,
              "status": "passed"
            },
            "line": 6,
            "name": "User click on Desktops tab",
            "match": {
              "location": "step.definition.DesktopStepDef.user_click_on_Desktops_tab()"
            },
            "keyword": "When "
          },
          {
            "result": {
              "error_message": "org.openqa.selenium.ElementNotInteractableException: element not interactable\n  (Session info: chrome\u003d101.0.4951.64)\nBuild info: version: \u00273.141.59\u0027, revision: \u0027e82be7d358\u0027, time: \u00272018-11-14T08:17:03\u0027\nSystem info: host: \u0027Sanas-MacBook-Air.local\u0027, ip: \u00272601:140:8c00:c6b0:0:0:0:4f00%en0\u0027, os.name: \u0027Mac OS X\u0027, os.arch: \u0027x86_64\u0027, os.version: \u002712.3.1\u0027, java.version: \u002717.0.2\u0027\nDriver info: org.openqa.selenium.chrome.ChromeDriver\nCapabilities {acceptInsecureCerts: false, browserName: chrome, browserVersion: 101.0.4951.64, chrome: {chromedriverVersion: 101.0.4951.41 (93c720db8323..., userDataDir: /var/folders/f8/fd7_q6bx49s...}, goog:chromeOptions: {debuggerAddress: localhost:54458}, javascriptEnabled: true, networkConnectionEnabled: false, pageLoadStrategy: normal, platform: MAC, platformName: MAC, proxy: Proxy(), setWindowRect: true, strictFileInteractability: false, timeouts: {implicit: 0, pageLoad: 300000, script: 30000}, unhandledPromptBehavior: dismiss and notify, webauthn:extension:credBlob: true, webauthn:extension:largeBlob: true, webauthn:virtualAuthenticators: true}\nSession ID: 3275aec5af656049bd477c0e2bac96f2\n\tat java.base/jdk.internal.reflect.NativeConstructorAccessorImpl.newInstance0(Native Method)\n\tat java.base/jdk.internal.reflect.NativeConstructorAccessorImpl.newInstance(NativeConstructorAccessorImpl.java:77)\n\tat java.base/jdk.internal.reflect.DelegatingConstructorAccessorImpl.newInstance(DelegatingConstructorAccessorImpl.java:45)\n\tat java.base/java.lang.reflect.Constructor.newInstanceWithCaller(Constructor.java:499)\n\tat java.base/java.lang.reflect.Constructor.newInstance(Constructor.java:480)\n\tat org.openqa.selenium.remote.http.W3CHttpResponseCodec.createException(W3CHttpResponseCodec.java:187)\n\tat org.openqa.selenium.remote.http.W3CHttpResponseCodec.decode(W3CHttpResponseCodec.java:122)\n\tat org.openqa.selenium.remote.http.W3CHttpResponseCodec.decode(W3CHttpResponseCodec.java:49)\n\tat org.openqa.selenium.remote.HttpCommandExecutor.execute(HttpCommandExecutor.java:158)\n\tat org.openqa.selenium.remote.service.DriverCommandExecutor.execute(DriverCommandExecutor.java:83)\n\tat org.openqa.selenium.remote.RemoteWebDriver.execute(RemoteWebDriver.java:552)\n\tat org.openqa.selenium.remote.RemoteWebElement.execute(RemoteWebElement.java:285)\n\tat org.openqa.selenium.remote.RemoteWebElement.click(RemoteWebElement.java:84)\n\tat java.base/jdk.internal.reflect.NativeMethodAccessorImpl.invoke0(Native Method)\n\tat java.base/jdk.internal.reflect.NativeMethodAccessorImpl.invoke(NativeMethodAccessorImpl.java:77)\n\tat java.base/jdk.internal.reflect.DelegatingMethodAccessorImpl.invoke(DelegatingMethodAccessorImpl.java:43)\n\tat java.base/java.lang.reflect.Method.invoke(Method.java:568)\n\tat org.openqa.selenium.support.pagefactory.internal.LocatingElementHandler.invoke(LocatingElementHandler.java:51)\n\tat jdk.proxy2/jdk.proxy2.$Proxy21.click(Unknown Source)\n\tat page.objects.DesktopsPage.clickOnShowAllDesktops(DesktopsPage.java:45)\n\tat step.definition.DesktopStepDef.user_click_On_Show_all_desktops(DesktopStepDef.java:36)\n\tat ✽.User click on Show all desktops(classpath:feature/Desktops.feature:7)\n",
              "duration": 30131326000,
              "status": "failed"
            },
            "line": 7,
            "name": "User click on Show all desktops",
            "match": {
              "location": "step.definition.DesktopStepDef.user_click_On_Show_all_desktops()"
            },
            "keyword": "And "
          }
        ]
      },
      {
        "start_timestamp": "2022-05-26T18:28:17.416Z",
        "before": [
          {
            "result": {
              "duration": 10385630000,
              "status": "passed"
            },
            "match": {
              "location": "step.definition.Initializer.beforeHooks(io.cucumber.java.Scenario)"
            }
          }
        ],
        "line": 14,
        "name": "User add HP LP 3065 from Desktops tab to the cart",
        "description": "",
        "id": "desktops;user-add-hp-lp-3065-from-desktops-tab-to-the-cart",
        "after": [
          {
            "result": {
              "duration": 228941000,
              "status": "passed"
            },
            "match": {
              "location": "step.definition.Initializer.afterHooks(io.cucumber.java.Scenario)"
            }
          }
        ],
        "type": "scenario",
        "keyword": "Scenario",
        "steps": [
          {
            "result": {
              "duration": 407000,
              "status": "skipped"
            },
            "line": 15,
            "name": "User click ADD TO CART option on ‘HP LP3065’ item",
            "match": {
              "location": "step.definition.DesktopStepDef.user_click_add_to_cart_option_on_hp_lp3065_item()"
            },
            "keyword": "And "
          },
          {
            "result": {
              "duration": 361000,
              "status": "skipped"
            },
            "line": 16,
            "name": "User select quantity 1",
            "match": {
              "arguments": [
                {
                  "val": "1",
                  "offset": 21
                }
              ],
              "location": "step.definition.DesktopStepDef.user_select_quantity(java.lang.Integer)"
            },
            "keyword": "And "
          },
          {
            "result": {
              "duration": 387000,
              "status": "skipped"
            },
            "line": 17,
            "name": "User click add to Cart button",
            "match": {
              "location": "step.definition.DesktopStepDef.user_click_add_to_cart_button()"
            },
            "keyword": "And "
          },
          {
            "result": {
              "duration": 1785000,
              "status": "skipped"
            },
            "line": 18,
            "name": "User should see a message ‘Success: you have added HP LP 3065 to your Shopping cart!’",
            "match": {
              "arguments": [
                {
                  "val": "3065",
                  "offset": 57
                }
              ],
              "location": "step.definition.DesktopStepDef.user_should_see_a_message_success_you_have_added_hp_lp_to_your_shopping_cart(java.lang.Integer)"
            },
            "keyword": "Then "
          }
        ],
        "tags": [
          {
            "name": "@TestallDesktopsFeatures"
          },
          {
            "name": "@addHP3065"
          }
        ]
      }
    ],
    "name": "Desktops",
    "description": "",
    "id": "desktops",
    "keyword": "Feature",
    "uri": "classpath:feature/Desktops.feature",
    "tags": [
      {
        "name": "@TestallDesktopsFeatures",
        "type": "Tag",
        "location": {
          "line": 1,
          "column": 1
        }
      }
    ]
  }
]